cum/__init__.py
cum/config.py
cum/cum.py
cum/db.py
cum/exceptions.py
cum/output.py
cum/sanity.py
cum/utility.py
cum/version.py
cum/scrapers/__init__.py
cum/scrapers/base.py
cum/scrapers/dokireader.py
cum/scrapers/dynastyscans.py
cum/scrapers/foolslide.py
cum/scrapers/madokami.py
cum/scrapers/mangadex.py
cum/scrapers/yuriism.py
cum-0.9.1.data/data/LICENSE
cum-0.9.1.data/data/tests/broken_config.json
cum-0.9.1.data/data/tests/broken_database.db
cum-0.9.1.dist-info/METADATA
cum-0.9.1.dist-info/RECORD
cum-0.9.1.dist-info/WHEEL
cum-0.9.1.dist-info/entry_points.txt
cum-0.9.1.dist-info/top_level.txt
tests/__init__.py
tests/cumtest.py
tests/test_cli_chapters.py
tests/test_cli_config.py
tests/test_cli_download.py
tests/test_cli_edit.py
tests/test_cli_follow.py
tests/test_cli_follows.py
tests/test_cli_get.py
tests/test_cli_ignore.py
tests/test_cli_latest.py
tests/test_cli_new.py
tests/test_cli_open.py
tests/test_cli_repair_db.py
tests/test_cli_unfollow.py
tests/test_cli_unignore.py
tests/test_cli_update.py
tests/test_scraper_dokireader.py
tests/test_scraper_dynastyscans.py
tests/test_scraper_madokami.py
tests/test_scraper_mangadex.py
tests/test_scraper_yuriism.py
