Metadata-Version: 2.1
Name: cum
Version: 0.9.1
Summary: comic updater, mangafied
Home-page: https://github.com/Hamuko/cum
Author: Hamuko
Author-email: hamuko@burakku.com
License: Apache2
Platform: UNKNOWN
Classifier: Development Status :: 5 - Production/Stable
Classifier: Environment :: Console
Classifier: Intended Audience :: End Users/Desktop
Classifier: License :: OSI Approved :: Apache Software License
Classifier: Programming Language :: Python :: 3
Classifier: Programming Language :: Python :: 3.3
Classifier: Programming Language :: Python :: 3.4
Classifier: Programming Language :: Python :: 3.5
Classifier: Topic :: Internet :: WWW/HTTP
Provides-Extra: testing
Requires-Dist: alembic
Requires-Dist: beautifulsoup4
Requires-Dist: Click
Requires-Dist: natsort
Requires-Dist: requests
Requires-Dist: SQLAlchemy
Provides-Extra: testing
Requires-Dist: codecov; extra == 'testing'
Requires-Dist: cov-core; extra == 'testing'
Requires-Dist: nose2; extra == 'testing'
Requires-Dist: pycodestyle; extra == 'testing'
